cpm_file/main.py
cpm_file/src/parse_file_word/__init__.py
cpm_file/src/parse_file_word/parse_word.py
cpm_file-2.6.dist-info/LICENSE
cpm_file-2.6.dist-info/METADATA
cpm_file-2.6.dist-info/WHEEL
cpm_file-2.6.dist-info/entry_points.txt
cpm_file-2.6.dist-info/top_level.txt
cpm_file-2.6.dist-info/RECORD
