Metadata-Version: 2.1
Name: cpm-file
Version: 2.6
Summary: Finding substrings in the lines of a file.
Home-page: UNKNOWN
Author: Laura Pérez Vera
Author-email: lpvera22@gmail.com
License: MIT
Keywords: search keyword substring research substring
Platform: UNKNOWN
Classifier: Programming Language :: Python :: 3
Classifier: License :: OSI Approved :: MIT License
Classifier: Operating System :: OS Independent
